otcdocstheme/__init__.py
otcdocstheme/ext.py
otcdocstheme/page_context.py
otcdocstheme/paths.py
otcdocstheme/version.py
otcdocstheme/theme/otcdocs/__init__.py
otcdocstheme/theme/otcdocs/css.html
otcdocstheme/theme/otcdocs/footer.html
otcdocstheme/theme/otcdocs/header.html
otcdocstheme/theme/otcdocs/layout.html
otcdocstheme/theme/otcdocs/license_cc.html
otcdocstheme/theme/otcdocs/localtoc.html
otcdocstheme/theme/otcdocs/script_footer.html
otcdocstheme/theme/otcdocs/script_search.html
otcdocstheme/theme/otcdocs/search.html
otcdocstheme/theme/otcdocs/sidebartoc.html
otcdocstheme/theme/otcdocs/sidebartoc_menu.html
otcdocstheme/theme/otcdocs/sidebartoc_menu_apiref.html
otcdocstheme/theme/otcdocs/swiftype_search.html
otcdocstheme/theme/otcdocs/swiftype_search_install.html
otcdocstheme/theme/otcdocs/swiftype_search_mobile.html
otcdocstheme/theme/otcdocs/theme.conf
otcdocstheme/theme/otcdocs/titlerow.html
otcdocstheme/theme/otcdocs/_pygments/style.py
otcdocstheme/theme/otcdocs/static/favicon.ico
otcdocstheme/theme/otcdocs/static/package.json
otcdocstheme/theme/otcdocs/static/css/bootstrap.min.css
otcdocstheme/theme/otcdocs/static/css/bootstrap.min.css.map
otcdocstheme/theme/otcdocs/static/css/fontawesome-all.min.css
otcdocstheme/theme/otcdocs/static/css/otcdocstheme.css
otcdocstheme/theme/otcdocs/static/fonts/.gitkeep
otcdocstheme/theme/otcdocs/static/fonts/glyphicons-halflings-regular.eot
otcdocstheme/theme/otcdocs/static/fonts/glyphicons-halflings-regular.svg
otcdocstheme/theme/otcdocs/static/fonts/glyphicons-halflings-regular.ttf
otcdocstheme/theme/otcdocs/static/fonts/glyphicons-halflings-regular.woff
otcdocstheme/theme/otcdocs/static/fonts/glyphicons-halflings-regular.woff2
otcdocstheme/theme/otcdocs/static/images/deutsche-telekom-logo.svg
otcdocstheme/theme/otcdocs/static/images/dt-de.svg
otcdocstheme/theme/otcdocs/static/images/dt-en.svg
otcdocstheme/theme/otcdocs/static/images/dt.svg
otcdocstheme/theme/otcdocs/static/images/loading.gif
otcdocstheme-1.13.3.dist-info/licenses/AUTHORS
otcdocstheme-1.13.3.dist-info/licenses/LICENSE
otcdocstheme-1.13.3.dist-info/METADATA
otcdocstheme-1.13.3.dist-info/WHEEL
otcdocstheme-1.13.3.dist-info/dependency_links.txt
otcdocstheme-1.13.3.dist-info/entry_points.txt
otcdocstheme-1.13.3.dist-info/pbr.json
otcdocstheme-1.13.3.dist-info/top_level.txt
otcdocstheme-1.13.3.dist-info/RECORD
