Metadata-Version: 2.4
Name: otcdocstheme
Version: 1.13.3
Summary: OpenTelekomCloud Docs Theme
Home-page: https://cloud.otc.com
Author: Artem Goncharov
Author-email: artem.goncharov@gmail.com
Classifier: Environment :: OpenStack
Classifier: Environment :: Other Environment
Classifier: Intended Audience :: Information Technology
Classifier: Intended Audience :: System Administrators
Classifier: License :: OSI Approved :: Apache Software License
Classifier: Operating System :: POSIX :: Linux
Classifier: Programming Language :: Python
Classifier: Programming Language :: Python :: 3
Classifier: Programming Language :: Python :: 3.5
Classifier: Programming Language :: Python :: 3.6
Classifier: Programming Language :: Python :: 3.7
Classifier: Programming Language :: Python :: 3.8
Classifier: Topic :: Documentation
Requires-Python: >= 3.6
License-File: LICENSE
License-File: AUTHORS
Requires-Dist: pbr!=2.1.0,>=2.0.0
Requires-Dist: dulwich>=0.15.0
Requires-Dist: setuptools
Requires-Dist: otc-metadata
Dynamic: author
Dynamic: author-email
Dynamic: classifier
Dynamic: description
Dynamic: home-page
Dynamic: license-file
Dynamic: requires-dist
Dynamic: requires-python
Dynamic: summary
